mbutil/__init__.py
mbutil/util.py
mbutil-0.3.0.data/scripts/mb-util
mbutil-0.3.0.dist-info/DESCRIPTION.rst
mbutil-0.3.0.dist-info/METADATA
mbutil-0.3.0.dist-info/RECORD
mbutil-0.3.0.dist-info/WHEEL
mbutil-0.3.0.dist-info/metadata.json
mbutil-0.3.0.dist-info/top_level.txt
