Metadata-Version: 1.0
Name: mbutil
Version: 0.3.0
Summary: An importer and exporter for MBTiles
Home-page: https://github.com/mapbox/mbutil
Author: Tom MacWright
Author-email: tom@macwright.org
License: LICENSE.md
Platform: UNKNOWN
